mux/8_isto_1_mux/mux_8_1.v
module mux_8_1(
    input D1,
    input D2,
    input D3,
    input D4,
    input D5,
    input D6,
    input D7,
    input D8,
    input S1,
    input S2,
    input S3,
    output q
);
assign q= (~S1&~S2&~S3&D1)|(~S1&~S2&S3&D2)|(~S1&S2&~S3&D3)|(~S1&S2&S3&D4)|
         (S1&~S2&~S3&D5)|(S1&~S2&S3&D6)|(S1&S2&~S3&D7)|(S1&S2&S3&D8);
endmodule

mux/8_isto_1_mux/mux_8_1_tb.v
`timescale 1ps/1ps
module mux_8_1_tb;
    reg D1,D2,D3,D4,D5,D6,D7,D8,S1,S2,S3;
    wire q;  
    mux_8_1 uut(
    .D1(D1),
    .D2(D2),
    .D3(D3),
    .D4(D4),
    .D5(D5),
    .D6(D6),
    .D7(D7),
    .D8(D8),
    .S1(S1),
    .S2(S2),
    .S3(S3),
    .q(q)
    );
    initial begin 
        $dumpfile("mux_8_1.vcd");
        $dumpvars(0,mux_8_1_tb);

        S1=0; S2=0; S3=0; D1=1; D2=0; D3=0; D4=0; D5=0; D6=0; D7=0; D8=0; #10;
        S1=0; S2=0; S3=1; D1=0; D2=1; D3=0; D4=0; D5=0; D6=0; D7=0; D8=0; #10;
        S1=0; S2=1; S3=0; D1=0; D2=0; D3=1; D4=0; D5=0; D6=0; D7=0; D8=0; #10;
        S1=0; S2=1; S3=1; D1=0; D2=0; D3=0; D4=1; D5=0; D6=0; D7=0; D8=0; #10; 
        S1=1; S2=0; S3=0; D1=0; D2=0; D3=0; D4=0; D5=1; D6=0; D7=0; D8=0; #10;
        S1=1; S2=1; S3=1; D1=0; D2=0; D3=0; D4=0; D5=0; D6=1; D7=0; D8=0; #10;
        S1=1; S2=0; S3=0; D1=0; D2=0; D3=0; D4=0; D5=0; D6=0; D7=1; D8=0; #10;
        S1=1; S2=0; S3=1; D1=0; D2=0; D3=0; D4=0; D5=0; D6=0; D7=0; D8=1; #10;
        $finish;
    end
endmodule

mux/8_isto_1_mux/mux_8_1.vcd
$date
	Thu Jan 09 12:50:05 2025
$end
$version
	Icarus Verilog
$end
$timescale
	1ps
$end
$scope module mux_8_1_tb $end
$var wire 1 ! q $end
$var reg 1 " D1 $end
$var reg 1 # D2 $end
$var reg 1 $ D3 $end
$var reg 1 % D4 $end
$var reg 1 & D5 $end
$var reg 1 ' D6 $end
$var reg 1 ( D7 $end
$var reg 1 ) D8 $end
$var reg 1 * S1 $end
$var reg 1 + S2 $end
$var reg 1 , S3 $end
$scope module uut $end
$var wire 1 " D1 $end
$var wire 1 # D2 $end
$var wire 1 $ D3 $end
$var wire 1 % D4 $end
$var wire 1 & D5 $end
$var wire 1 ' D6 $end
$var wire 1 ( D7 $end
$var wire 1 ) D8 $end
$var wire 1 * S1 $end
$var wire 1 + S2 $end
$var wire 1 , S3 $end
$var wire 1 ! q $end
$upscope $end
$upscope $end
$enddefinitions $end
$comment Show the parameter values. $end
$dumpall
$end
#0
$dumpvars
0,
0+
0*
0)
0(
0'
0&
0%
0$
0#
1"
1!
$end
#10
1#
0"
1,
#20
1$
0#
0,
1+
#30
1%
0$
1,
#40
1&
0%
0,
0+
1*
#50
0!
1'
0&
1,
1+
#60
1(
0'
0,
0+
#70
1)
0(
1,
