demux/demux_1_4/demux_1_4.v
module demux_1_4(
    input a,
    input b,
    input F,
    output A,
    output B,
    output C,
    output D
);
assign A = (~a & ~b & F);
assign B = (~a & b & F);
assign C = (a & ~b & F);
assign D = (a & b & F);
endmodule

demux/demux_1_4/demux_1_4_tb.v
`timescale 1ps/1ps
module demux_1_4_tb;
    reg a,b,F;
    wire A,B,C,D;
    demux_1_4 uut(
        .a(a),
        .b(b),
        .F(F),
        .A(A),
        .B(B),
        .C(C),
        .D(D)
    );
    initial begin
        $dumpfile("demux_1_4.vcd");
        $dumpvars(0,demux_1_4_tb);

        a=0; b=0; F=0; #10;
        a=0; b=0; F=1; #10;
        a=0; b=1; F=0; #10;
        a=0; b=1; F=1; #10;
        a=1; b=0; F=0; #10;
        a=1; b=0; F=1; #10;
        a=1; b=1; F=0; #10;
        a=1; b=1; F=1; #10;
        $finish;
    end
endmodule

demux/demux_1_4/demux_1_4.vcd
$date
	Thu Jan 09 14:08:07 2025
$end
$version
	Icarus Verilog
$end
$timescale
	1ps
$end
$scope module demux_1_4_tb $end
$var wire 1 ! D $end
$var wire 1 " C $end
$var wire 1 # B $end
$var wire 1 $ A $end
$var reg 1 % F $end
$var reg 1 & a $end
$var reg 1 ' b $end
$scope module uut $end
$var wire 1 $ A $end
$var wire 1 # B $end
$var wire 1 " C $end
$var wire 1 ! D $end
$var wire 1 % F $end
$var wire 1 & a $end
$var wire 1 ' b $end
$upscope $end
$upscope $end
$enddefinitions $end
$comment Show the parameter values. $end
$dumpall
$end
#0
$dumpvars
0'
0&
0%
0$
0#
0"
0!
$end
#10
1$
1%
#20
0$
0%
1'
#30
1#
1%
#40
0#
0%
0'
1&
#50
1"
1%
#60
0"
0%
1'
#70
1!
1%
