p1/p1.v
module p1(
    input a,
    input b,
    input c,
    input d,
    output q
);
wire and1_out , and2_out;
and and1(and1_out , a , b);

and and2(and2_out ,c ,d);

or or1(q , and1_out , and2_out);

endmodule

p1/p1_tb.v
`timescale 1ns/1ps
module p1_tb;
    reg a, b, c, d;
    wire q;

    p1 uut (
        .a(a),
        .b(b),
        .c(c),
        .d(d),
        .q(q)
    );

    initial begin
        $monitor("a=%b , b=%b , c=%b , d=%b, q=%b", a, b, c, d, q);
        $dumpfile ("p1.vcd");
        $dumpvars (0,p1_tb);

        a = 0; b = 0; c = 0; d = 0; #10;
        a = 0; b = 0; c = 0; d = 1; #10;
        a = 0; b = 0; c = 1; d = 0; #10;
        a = 0; b = 0; c = 1; d = 1; #10;
        a = 0; b = 1; c = 0; d = 0; #10;
        a = 0; b = 1; c = 0; d = 1; #10;
        a = 1; b = 0; c = 0; d = 0; #10;
        a = 1; b = 0; c = 0; d = 1; #10;
        a = 1; b = 1; c = 0; d = 0; #10;
        a = 1; b = 1; c = 0; d = 1; #10;
        a = 1; b = 1; c = 1; d = 0; #10;
        a = 1; b = 1; c = 1; d = 1; #10;
        $finish;
    end
endmodule

p1/p1.vcd
$date
	Wed Jan 08 16:54:53 2025
$end
$version
	Icarus Verilog
$end
$timescale
	1ps
$end
$scope module p1_tb $end
$var wire 1 ! q $end
$var reg 1 " a $end
$var reg 1 # b $end
$var reg 1 $ c $end
$var reg 1 % d $end
$scope module uut $end
$var wire 1 " a $end
$var wire 1 & and1_out $end
$var wire 1 ' and2_out $end
$var wire 1 # b $end
$var wire 1 $ c $end
$var wire 1 % d $end
$var wire 1 ! q $end
$upscope $end
$upscope $end
$enddefinitions $end
$comment Show the parameter values. $end
$dumpall
$end
#0
$dumpvars
0'
0&
0%
0$
0#
0"
0!
$end
#10000
1%
#20000
0%
1$
#30000
1!
1'
1%
#40000
0!
0'
0%
0$
1#
#50000
1%
#60000
0%
0#
1"
#70000
1%
#80000
1!
1&
0%
1#
#90000
1%
#100000
0%
1$
#110000
1'
1%
