encoder/encoder.v
module priority_encoder_8_to_3 (
    input [7:0] in,
    output reg [2:0] out
);
always @(*) begin
    casex (in)
        8'b00000001: out = 3'b000;
        8'b0000001x: out = 3'b001;
        8'b000001xx: out = 3'b010;
        8'b00001xxx: out = 3'b011;
        8'b0001xxxx: out = 3'b100;
        8'b001xxxxx: out = 3'b101;
        8'b01xxxxxx: out = 3'b110;
        8'b1xxxxxxx: out = 3'b111;
        default: out = 3'b000;
    endcase
end
endmodule

encoder/encoder_tb.v
`timescale 1ns/1ps

module priority_encoder_8_to_3_tb;
    reg [7:0] in;
    wire [2:0] out;

    priority_encoder_8_to_3 uut (
        .in(in),
        .out(out)
    );

    initial begin
        $dumpfile("priority_encoder_8_to_3.vcd");
        $dumpvars(0, priority_encoder_8_to_3_tb);

        in = 8'b00000001; #10;
        in = 8'b00000010; #10;
        in = 8'b00000100; #10;
        in = 8'b00001000; #10;
        in = 8'b00010000; #10;
        in = 8'b00100000; #10;
        in = 8'b01000000; #10;
        in = 8'b10000000; #10;
        in = 8'b00000011; #10;
        in = 8'b00000111; #10;
        in = 8'b00001111; #10;
        in = 8'b00011111; #10;
        in = 8'b00111111; #10;
        in = 8'b01111111; #10;
        in = 8'b11111111; #10;

        $finish;
    end
endmodule

encoder/priority_encoder_8_to_3.vcd
$date
	Thu Jan 09 14:48:55 2025
$end
$version
	Icarus Verilog
$end
$timescale
	1ps
$end
$scope module priority_encoder_8_to_3_tb $end
$var wire 3 ! out [2:0] $end
$var reg 8 " in [7:0] $end
$scope module uut $end
$var wire 8 # in [7:0] $end
$var reg 3 $ out [2:0] $end
$upscope $end
$upscope $end
$enddefinitions $end
$comment Show the parameter values. $end
$dumpall
$end
#0
$dumpvars
b0 $
b1 #
b1 "
b0 !
$end
#10000
b1 !
b1 $
b10 "
b10 #
#20000
b10 !
b10 $
b100 "
b100 #
#30000
b11 !
b11 $
b1000 "
b1000 #
#40000
b100 !
b100 $
b10000 "
b10000 #
#50000
b101 !
b101 $
b100000 "
b100000 #
#60000
b110 !
b110 $
b1000000 "
b1000000 #
#70000
b111 !
b111 $
b10000000 "
b10000000 #
#80000
b1 !
b1 $
b11 "
b11 #
#90000
b10 !
b10 $
b111 "
b111 #
#100000
b11 !
b11 $
b1111 "
b1111 #
#110000
b100 !
b100 $
b11111 "
b11111 #
#120000
b101 !
b101 $
b111111 "
b111111 #
#130000
b110 !
b110 $
b1111111 "
b1111111 #
#140000
b111 !
b111 $
b11111111 "
b11111111 #
