demux/demux_1_8/demux_1_8.v
module demux_1_8(
    input a,
    input b,
    input c,
    input D,
    output Y1,
    output Y2,
    output Y3,
    output Y4,
    output Y5,
    output Y6,
    output Y7,
    output Y8
);
assign Y1 = (~a & ~b & ~c & D);
assign Y2 = (~a & ~b & c & D);
assign Y3 = (~a & b & ~c & D);
assign Y4 = (~a & b & c & D);
assign Y5 = (a & ~b & ~c & D);
assign Y6 = (a & ~b & c & D);
assign Y7 = (a & b & ~c & D);
assign Y8 = (a & b & c & D);
endmodule

demux/demux_1_8/demux_1_8_tb.v
`timescale 1ps/1ps
module demux_1_8_tb;
    reg a,b,c,D;
    wire Y1,Y2,Y3,Y4,Y5,Y6,Y7,Y8;
    demux_1_8 uut(
        .a(a),
        .b(b),
        .c(c),
        .D(D),
        .Y1(Y1),
        .Y2(Y2),
        .Y3(Y3),
        .Y4(Y4),
        .Y5(Y5),
        .Y6(Y6),
        .Y7(Y7),
        .Y8(Y8)
    );
    initial begin
        $dumpfile("demux_1_8.vcd");
        $dumpvars(0,demux_1_8_tb);

        a=0; b=0; c=0; D=0; #10;
        a=0; b=0; c=0; D=1; #10;
        a=0; b=0; c=1; D=0; #10;
        a=0; b=0; c=1; D=1; #10;
        a=0; b=1; c=0; D=0; #10;
        a=0; b=1; c=0; D=1; #10;
        a=0; b=1; c=1; D=0; #10;
        a=0; b=1; c=1; D=1; #10;
        a=1; b=0; c=0; D=0; #10;
        a=1; b=0; c=0; D=1; #10;
        a=1; b=0; c=1; D=0; #10;
        a=1; b=0; c=1; D=1; #10;
        a=1; b=1; c=0; D=0; #10;
        a=1; b=1; c=0; D=1; #10;
        a=1; b=1; c=1; D=0; #10;
        a=1; b=1; c=1; D=1; #10;
        $finish;
    end
endmodule

demux/demux_1_8/demux_1_8.vcd
$date
	Thu Jan 09 14:29:30 2025
$end
$version
	Icarus Verilog
$end
$timescale
	1ps
$end
$scope module demux_1_8_tb $end
$var wire 1 ! Y8 $end
$var wire 1 " Y7 $end
$var wire 1 # Y6 $end
$var wire 1 $ Y5 $end
$var wire 1 % Y4 $end
$var wire 1 & Y3 $end
$var wire 1 ' Y2 $end
$var wire 1 ( Y1 $end
$var reg 1 ) D $end
$var reg 1 * a $end
$var reg 1 + b $end
$var reg 1 , c $end
$scope module uut $end
$var wire 1 ) D $end
$var wire 1 ( Y1 $end
$var wire 1 ' Y2 $end
$var wire 1 & Y3 $end
$var wire 1 % Y4 $end
$var wire 1 $ Y5 $end
$var wire 1 # Y6 $end
$var wire 1 " Y7 $end
$var wire 1 ! Y8 $end
$var wire 1 * a $end
$var wire 1 + b $end
$var wire 1 , c $end
$upscope $end
$upscope $end
$enddefinitions $end
$comment Show the parameter values. $end
$dumpall
$end
#0
$dumpvars
0,
0+
0*
0)
0(
0'
0&
0%
0$
0#
0"
0!
$end
#10
1(
1)
#20
0(
0)
1,
#30
1'
1)
#40
0'
0)
0,
1+
#50
1&
1)
#60
0&
0)
1,
#70
1%
1)
#80
0%
0)
0,
0+
1*
#90
1$
1)
#100
0$
0)
1,
#110
1#
1)
#120
0#
0)
0,
1+
#130
1"
1)
#140
0"
0)
1,
#150
1!
1)
